drawingletters/__init__.py
drawingletters-0.1.0.dist-info/METADATA
drawingletters-0.1.0.dist-info/WHEEL
drawingletters-0.1.0.dist-info/top_level.txt
drawingletters-0.1.0.dist-info/RECORD
